{
  "environment": "controlled",
  "temperature": 6.4,
  "humidity": 85.5,
  "light_type": "none",
  "date_started": "2026-05-30",
  "day_index": 14,
  "days_remaining": 7,
  "brix": [
    13.54,
    13.26,
    13.48
  ],
  "ph": [
    4.48,
    4.62,
    4.63
  ],
  "texture": [
    32.43,
    33.12,
    32.76
  ],
  "weight_loss": [
    5.75,
    5.52,
    5.1
  ],
  "ripeness_index": [
    3.68,
    3.67,
    3.82
  ],
  "images": [
    ".\\data\\mango\\controlled-environment\\non-destructive\\day-14\\cbd3img1d14.png",
    ".\\data\\mango\\controlled-environment\\non-destructive\\day-14\\cbd3img2d14.png"
  ]
}